{
  "Version": 1,
  "WorkspaceRootPath": "D:\\RapidApplication\\RAD_Assignment\\",
  "Documents": [
    {
      "AbsoluteMoniker": "D:0:0:{C6EEF5FE-5999-474B-B8C7-0F98D7325DD2}|RAD_Assignment.csproj|D:\\RapidApplication\\RAD_Assignment\\form1.cs||{A6C744A8-0E4A-4FC6-886A-064283054674}",
      "RelativeMoniker": "D:0:0:{C6EEF5FE-5999-474B-B8C7-0F98D7325DD2}|RAD_Assignment.csproj|solutionrelative:form1.cs||{A6C744A8-0E4A-4FC6-886A-064283054674}"
    },
    {
      "AbsoluteMoniker": "D:0:0:{C6EEF5FE-5999-474B-B8C7-0F98D7325DD2}|RAD_Assignment.csproj|D:\\RapidApplication\\RAD_Assignment\\addplayerform.cs||{A6C744A8-0E4A-4FC6-886A-064283054674}",
      "RelativeMoniker": "D:0:0:{C6EEF5FE-5999-474B-B8C7-0F98D7325DD2}|RAD_Assignment.csproj|solutionrelative:addplayerform.cs||{A6C744A8-0E4A-4FC6-886A-064283054674}"
    },
    {
      "AbsoluteMoniker": "D:0:0:{C6EEF5FE-5999-474B-B8C7-0F98D7325DD2}|RAD_Assignment.csproj|d:\\rapidapplication\\rad_assignment\\players.cs||{A6C744A8-0E4A-4FC6-886A-064283054674}",
      "RelativeMoniker": "D:0:0:{C6EEF5FE-5999-474B-B8C7-0F98D7325DD2}|RAD_Assignment.csproj|solutionrelative:players.cs||{A6C744A8-0E4A-4FC6-886A-064283054674}"
    },
    {
      "AbsoluteMoniker": "D:0:0:{C6EEF5FE-5999-474B-B8C7-0F98D7325DD2}|RAD_Assignment.csproj|D:\\RapidApplication\\RAD_Assignment\\form1.cs||{A6C744A8-0E4A-4FC6-886A-064283054674}|Form",
      "RelativeMoniker": "D:0:0:{C6EEF5FE-5999-474B-B8C7-0F98D7325DD2}|RAD_Assignment.csproj|solutionrelative:form1.cs||{A6C744A8-0E4A-4FC6-886A-064283054674}|Form"
    },
    {
      "AbsoluteMoniker": "D:0:0:{C6EEF5FE-5999-474B-B8C7-0F98D7325DD2}|RAD_Assignment.csproj|D:\\RapidApplication\\RAD_Assignment\\addplayerform.cs||{A6C744A8-0E4A-4FC6-886A-064283054674}|Form",
      "RelativeMoniker": "D:0:0:{C6EEF5FE-5999-474B-B8C7-0F98D7325DD2}|RAD_Assignment.csproj|solutionrelative:addplayerform.cs||{A6C744A8-0E4A-4FC6-886A-064283054674}|Form"
    }
  ],
  "DocumentGroupContainers": [
    {
      "Orientation": 0,
      "VerticalTabListWidth": 256,
      "DocumentGroups": [
        {
          "DockedWidth": 200,
          "SelectedChildIndex": 3,
          "Children": [
            {
              "$type": "Bookmark",
              "Name": "ST:0:0:{b1e99781-ab81-11d0-b683-00aa00a3ee26}"
            },
            {
              "$type": "Document",
              "DocumentIndex": 1,
              "Title": "AddPlayerForm.cs",
              "DocumentMoniker": "D:\\RapidApplication\\RAD_Assignment\\AddPlayerForm.cs",
              "RelativeDocumentMoniker": "AddPlayerForm.cs",
              "ToolTip": "D:\\RapidApplication\\RAD_Assignment\\AddPlayerForm.cs",
              "RelativeToolTip": "AddPlayerForm.cs",
              "ViewState": "AQIAAHAAAAAAAAAAAAAkwBEAAAAOAAAA",
              "Icon": "ae27a6b0-e345-4288-96df-5eaf394ee369.000738|",
              "WhenOpened": "2024-12-01T07:17:16.143Z",
              "EditorCaption": ""
            },
            {
              "$type": "Document",
              "DocumentIndex": 4,
              "Title": "AddPlayerForm.cs [Design]",
              "DocumentMoniker": "D:\\RapidApplication\\RAD_Assignment\\AddPlayerForm.cs",
              "RelativeDocumentMoniker": "AddPlayerForm.cs",
              "ToolTip": "D:\\RapidApplication\\RAD_Assignment\\AddPlayerForm.cs [Design]",
              "RelativeToolTip": "AddPlayerForm.cs [Design]",
              "Icon": "ae27a6b0-e345-4288-96df-5eaf394ee369.000738|",
              "WhenOpened": "2024-12-01T07:05:47.787Z",
              "EditorCaption": " [Design]"
            },
            {
              "$type": "Document",
              "DocumentIndex": 0,
              "Title": "Form1.cs",
              "DocumentMoniker": "D:\\RapidApplication\\RAD_Assignment\\Form1.cs",
              "RelativeDocumentMoniker": "Form1.cs",
              "ToolTip": "D:\\RapidApplication\\RAD_Assignment\\Form1.cs",
              "RelativeToolTip": "Form1.cs",
              "ViewState": "AQIAALsAAAAAAAAAAAAwwAcAAAAPAAAA",
              "Icon": "ae27a6b0-e345-4288-96df-5eaf394ee369.000738|",
              "WhenOpened": "2024-11-30T09:52:31.124Z",
              "EditorCaption": ""
            },
            {
              "$type": "Document",
              "DocumentIndex": 3,
              "Title": "Form1.cs [Design]",
              "DocumentMoniker": "D:\\RapidApplication\\RAD_Assignment\\Form1.cs",
              "RelativeDocumentMoniker": "Form1.cs",
              "ToolTip": "D:\\RapidApplication\\RAD_Assignment\\Form1.cs [Design]",
              "RelativeToolTip": "Form1.cs [Design]",
              "Icon": "ae27a6b0-e345-4288-96df-5eaf394ee369.000738|",
              "WhenOpened": "2024-11-30T09:16:54.922Z",
              "EditorCaption": " [Design]"
            },
            {
              "$type": "Document",
              "DocumentIndex": 2,
              "Title": "Players.cs",
              "DocumentMoniker": "D:\\RapidApplication\\RAD_Assignment\\Players.cs",
              "RelativeDocumentMoniker": "Players.cs",
              "ToolTip": "D:\\RapidApplication\\RAD_Assignment\\Players.cs",
              "RelativeToolTip": "Players.cs",
              "ViewState": "AQIAAAAAAAAAAAAAAAAAACYAAABYAAAA",
              "Icon": "ae27a6b0-e345-4288-96df-5eaf394ee369.000738|",
              "WhenOpened": "2024-11-30T09:33:28.315Z",
              "EditorCaption": ""
            }
          ]
        }
      ]
    }
  ]
}